knovleks/__init__.py
knovleks/__main__.py
knovleks/idocument_type.py
knovleks/knovleks.py
knovleks/tui.py
knovleks/document_types/__init__.py
knovleks/document_types/note_document.py
knovleks/document_types/pdf_document.py
knovleks/document_types/website_document.py
knovleks-0.0.4.dist-info/LICENSE
knovleks-0.0.4.dist-info/METADATA
knovleks-0.0.4.dist-info/WHEEL
knovleks-0.0.4.dist-info/entry_points.txt
knovleks-0.0.4.dist-info/top_level.txt
knovleks-0.0.4.dist-info/RECORD
