Metadata-Version: 2.1
Name: knovleks
Version: 0.0.4
Author: Loris Reiff
Author-email: loris.reiff@liblor.ch
License: Apache 2.0
License-File: LICENSE
Requires-Dist: PyMuPDF (==1.21.1)
Requires-Dist: newspaper3k (==0.2.8)
Requires-Dist: click (==8.1.3)
Requires-Dist: textual (==0.1.18)
Requires-Dist: textual-inputs (==0.2.6)
